{
	"projects": [
		{
			"name": "Some Project",
			"enable": true,
			"rules": [
				{"enable":true, "type":"file", 	"pattern":"http://www.qq.com/test", 	"replace":"D:\\test.txt"},
				{"enable":true, "type":"file",		"pattern":"http://www.qq.com/match/*",	"replace":"D:\\test.txt"},
				{"enable":true, "type":"dir", 		"pattern":"http://www.qq.com/test/", 	"replace":"D:\\test"},
				{"enable":true, "type":"combine",	"pattern":"http://www.qq.com/abc.js",	"replace":"D:\\test.qzmin"}
			]
		}
	]
}